CNPJ/__init__.py
PyCNPJ-0.0.3.dist-info/DESCRIPTION.rst
PyCNPJ-0.0.3.dist-info/METADATA
PyCNPJ-0.0.3.dist-info/RECORD
PyCNPJ-0.0.3.dist-info/WHEEL
PyCNPJ-0.0.3.dist-info/metadata.json
PyCNPJ-0.0.3.dist-info/top_level.txt
