Metadata-Version: 2.0
Name: PyCNPJ
Version: 0.0.3
Summary: Python lib to retrieve Brazilian companys information
Home-page: https://github.com/FRReinert/ConsultaCNPJ
Author: Fabricio Roberto reinert
Author-email: fabricio.reinert@live.com
License: MIT license
Keywords: CNPJ,CGC,Python,Requests
Platform: UNKNOWN
Classifier: Development Status :: 2 - Pre-Alpha
Classifier: Intended Audience :: Developers
Classifier: License :: OSI Approved :: MIT License
Classifier: Natural Language :: English
Classifier: Programming Language :: Python :: 3.6
Requires-Dist: requests
